psyop/__init__.py
psyop/main.py
psyop/model.py
psyop/opt.py
psyop/util.py
psyop/viz.py
psyop-0.1.0a5.dist-info/LICENSE
psyop-0.1.0a5.dist-info/METADATA
psyop-0.1.0a5.dist-info/WHEEL
psyop-0.1.0a5.dist-info/entry_points.txt
psyop-0.1.0a5.dist-info/RECORD
