Metadata-Version: 2.3
Name: psyop
Version: 0.1.0a5
Summary: Parameter Space Yield Optimizer
License: Apache-2.0
Keywords: command-line interface
Author: Robert Turnbull
Author-email: robert.turnbull@unimelb.edu.au
Requires-Python: >=3.10,<3.14
Classifier: Intended Audience :: Science/Research
Classifier: License :: OSI Approved :: Apache Software License
Classifier: Programming Language :: Python :: 3
Classifier: Programming Language :: Python :: 3.10
Classifier: Programming Language :: Python :: 3.11
Classifier: Programming Language :: Python :: 3.12
Classifier: Programming Language :: Python :: 3.13
Classifier: Topic :: Scientific/Engineering :: Artificial Intelligence
Classifier: Topic :: Software Development :: Libraries :: Python Modules
Requires-Dist: kaleido (==0.2.1)
Requires-Dist: pandas (>=2.3.0)
Requires-Dist: plotly (>=5.24.1)
Requires-Dist: pymc (>=5.18.1)
Requires-Dist: typer (>=0.15.1)
Project-URL: Documentation, https://rbturnbull.github.io/psyop
Project-URL: Homepage, https://github.com/rbturnbull/psyop/
Project-URL: Repository, https://github.com/rbturnbull/psyop/
